google_cloud_utilities/__init__.py
google_cloud_utilities/gcp.py
google_cloud_utilities-0.8.9.dist-info/licenses/LICENSE
google_cloud_utilities-0.8.9.dist-info/METADATA
google_cloud_utilities-0.8.9.dist-info/WHEEL
google_cloud_utilities-0.8.9.dist-info/top_level.txt
google_cloud_utilities-0.8.9.dist-info/RECORD
