Metadata-Version: 2.4
Name: google_cloud_utilities
Version: 0.8.9
Summary: A few handy Python functions for interacting with Google Cloud Platform
Home-page: https://github.com/johnf1004/google_cloud_utilities
Author: John Foley
Author-email: johnf1004@yahoo.co.uk
License: MIT
Classifier: License :: OSI Approved :: MIT License
Classifier: Programming Language :: Python
Classifier: Programming Language :: Python :: 3
Classifier: Programming Language :: Python :: 3.9
Classifier: Programming Language :: Python :: Implementation :: CPython
Classifier: Programming Language :: Python :: Implementation :: PyPy
Requires-Python: >=3.9.7
License-File: LICENSE
Requires-Dist: google-cloud-bigquery>=3.4.2
Requires-Dist: google-cloud-secret-manager>=2.4.0
Requires-Dist: pandas>=2.2.2
Requires-Dist: python-dateutil>=2.8.2
Requires-Dist: google-auth>=2.30.0
Requires-Dist: google-cloud-iam
Dynamic: author
Dynamic: author-email
Dynamic: classifier
Dynamic: description
Dynamic: description-content-type
Dynamic: home-page
Dynamic: license
Dynamic: license-file
Dynamic: requires-dist
Dynamic: requires-python
Dynamic: summary
